window_recorder/__init__.py
window_recorder/cfg.py
window_recorder/recorder.py
window_recorder-0.3.0.dist-info/LICENSE.txt
window_recorder-0.3.0.dist-info/METADATA
window_recorder-0.3.0.dist-info/WHEEL
window_recorder-0.3.0.dist-info/top_level.txt
window_recorder-0.3.0.dist-info/RECORD
