Metadata-Version: 2.1
Name: window_recorder
Version: 0.3.0
Summary: Programatically video record a window as a context manager
Author-email: Sheng Zhong <zhsh@umich.edu>
Maintainer-email: Sheng Zhong <zhsh@umich.edu>
License: Copyright (c) 2024 Sheng Zhong
Project-URL: Homepage, https://github.com/LemonPi/window_recorder
Project-URL: Bug Reports, https://github.com/LemonPi/window_recorder/issues
Project-URL: Source, https://github.com/LemonPi/window_recorder
Keywords: video,recording
Classifier: Development Status :: 4 - Beta
Classifier: Intended Audience :: Developers
Classifier: License :: OSI Approved :: MIT License
Classifier: Programming Language :: Python :: 3
Classifier: Programming Language :: Python :: 3 :: Only
Requires-Python: >=3.7
License-File: LICENSE.txt
Requires-Dist: opencv-python
Requires-Dist: mss
Provides-Extra: test
Requires-Dist: pytest ; extra == 'test'
